parquet_converter/__init__.py
parquet_converter/analyzer.py
parquet_converter/cli.py
parquet_converter/config.py
parquet_converter/converter.py
parquet_converter/logging.py
parquet_converter/parser.py
parquet_converter/stats.py
parquet_converter/tests/__init__.py
parquet_converter/tests/test_analyzer.py
parquet_converter/tests/test_cli.py
parquet_converter/tests/test_config.py
parquet_converter/tests/test_converter.py
parquet_converter/tests/test_logging.py
parquet_converter/tests/test_performance.py
parquet_converter-0.2.1.dist-info/licenses/LICENSE
parquet_converter-0.2.1.dist-info/METADATA
parquet_converter-0.2.1.dist-info/WHEEL
parquet_converter-0.2.1.dist-info/entry_points.txt
parquet_converter-0.2.1.dist-info/top_level.txt
parquet_converter-0.2.1.dist-info/RECORD
