Metadata-Version: 2.4
Name: parquet-converter
Version: 0.2.1
Summary: A tool to convert text files to Parquet format
Author-email: Sami Adnan <sami.adnan@ndph.ox.ac.uk>
License-Expression: MIT
Project-URL: Homepage, https://github.com/sami5001/parquet-converter
Project-URL: Bug Tracker, https://github.com/sami5001/parquet-converter/issues
Classifier: Programming Language :: Python :: 3
Classifier: Operating System :: OS Independent
Requires-Python: >=3.8
License-File: LICENSE
Requires-Dist: pandas
Requires-Dist: numpy
Requires-Dist: polars
Requires-Dist: rich
Requires-Dist: humanize
Requires-Dist: python-dotenv
Requires-Dist: pyarrow
Requires-Dist: pydantic
Requires-Dist: pyyaml
Requires-Dist: tqdm
Requires-Dist: tabulate
Provides-Extra: test
Requires-Dist: pytest; extra == "test"
Requires-Dist: pytest-cov; extra == "test"
Provides-Extra: dev
Requires-Dist: parquet-converter[test]; extra == "dev"
Requires-Dist: pre-commit; extra == "dev"
Requires-Dist: black; extra == "dev"
Requires-Dist: isort; extra == "dev"
Requires-Dist: flake8; extra == "dev"
Requires-Dist: mypy; extra == "dev"
Requires-Dist: pandas-stubs; extra == "dev"
Requires-Dist: types-tqdm; extra == "dev"
Requires-Dist: types-PyYAML; extra == "dev"
Requires-Dist: types-python-dateutil; extra == "dev"
Requires-Dist: types-tabulate; extra == "dev"
Requires-Dist: types-setuptools; extra == "dev"
Dynamic: license-file
